MANIFEST.in
setup.py
django_history.egg-info/PKG-INFO
django_history.egg-info/SOURCES.txt
django_history.egg-info/dependency_links.txt
django_history.egg-info/requires.txt
django_history.egg-info/top_level.txt
djangohistory/__init__.py
djangohistory/apps.py
djangohistory/controllers.py
djangohistory/diff.py
djangohistory/fields.py
djangohistory/helpers.py
djangohistory/managers.py
djangohistory/middleware.py
djangohistory/models.py
djangohistory/signals.py
djangohistory/urls.py
djangohistory/views.py
djangohistory/templates/djangohistory/latest.html
djangohistory/tests/__init__.py