Metadata-Version: 1.0
Name: django-history
Version: 0.5
Summary: History for Django ORM data changes
Home-page: http://github.com/futurice/django-history
Author: Jussi Vaihia
Author-email: jussi.vaihia@futurice.com
License: BSD
Keywords: django model history undo
Platform: UNKNOWN
